spectools_ir/__init__.py
spectools_ir/flux_calculator/__init__.py
spectools_ir/flux_calculator/flux_calculator.py
spectools_ir/flux_calculator/helpers.py
spectools_ir/slab_fitter/__init__.py
spectools_ir/slab_fitter/config.json
spectools_ir/slab_fitter/helpers.py
spectools_ir/slab_fitter/output.py
spectools_ir/slab_fitter/slab_fitter.py
spectools_ir/slabspec/__init__.py
spectools_ir/slabspec/helpers.py
spectools_ir/slabspec/slabspec.py
spectools_ir/utils/__init__.py
spectools_ir/utils/utils.py
spectools_ir-1.0.1.dist-info/LICENSE
spectools_ir-1.0.1.dist-info/METADATA
spectools_ir-1.0.1.dist-info/WHEEL
spectools_ir-1.0.1.dist-info/top_level.txt
spectools_ir-1.0.1.dist-info/RECORD
