Metadata-Version: 2.1
Name: spectools-ir
Version: 1.0.1
Summary: Tools for analysis and modeling of IR spectra
Home-page: https://github.com/csalyk/spectools_ir
Author: Colette Salyk
Author-email: cosalyk@vassar.edu
License: UNKNOWN
Platform: UNKNOWN
Classifier: Development Status :: 4 - Beta
Classifier: Intended Audience :: Science/Research
Classifier: License :: OSI Approved :: MIT License
Classifier: Operating System :: OS Independent
Classifier: Programming Language :: Python
Classifier: Programming Language :: Python :: 3
Classifier: Topic :: Scientific/Engineering :: Astronomy
License-File: LICENSE
Requires-Dist: astropy (>=4.2)
Requires-Dist: emcee (>=3.0)
Requires-Dist: numpy (>=1)
Requires-Dist: pandas (>=0.24)
Requires-Dist: corner (>=2.1)
Requires-Dist: matplotlib (>=3)
Requires-Dist: astroquery (>0.4)
Requires-Dist: scipy (>=1.2)
Requires-Dist: IPython (>=7.4)
